clickhouse_migrations/__init__.py
clickhouse_migrations/clickhouse_cluster.py
clickhouse_migrations/command_line.py
clickhouse_migrations/defaults.py
clickhouse_migrations/exceptions.py
clickhouse_migrations/migration.py
clickhouse_migrations/migrator.py
clickhouse_migrations-0.9.1.dist-info/licenses/LICENSE
clickhouse_migrations-0.9.1.dist-info/METADATA
clickhouse_migrations-0.9.1.dist-info/WHEEL
clickhouse_migrations-0.9.1.dist-info/entry_points.txt
clickhouse_migrations-0.9.1.dist-info/top_level.txt
clickhouse_migrations-0.9.1.dist-info/RECORD
