Metadata-Version: 2.4
Name: clickhouse-migrations
Version: 0.9.1
Summary: Simple file-based migrations for clickhouse
Author-email: Aleh Strakachuk <zifter.ai+clickhouse.migrations@gmail.com>
License: MIT
Project-URL: Homepage, https://github.com/zifter/clickhouse-migrations
Project-URL: Source, https://github.com/zifter/clickhouse-migrations
Project-URL: Tracker, https://github.com/zifter/clickhouse-migrations/issues
Project-URL: Changelog, https://github.com/zifter/clickhouse-migrations/blob/main/CHANGELOG.md
Keywords: clickhouse,migrations
Classifier: Intended Audience :: Developers
Classifier: Programming Language :: Python
Classifier: Programming Language :: Python :: 3.9
Classifier: Programming Language :: Python :: 3.10
Classifier: Programming Language :: Python :: 3.11
Classifier: Programming Language :: Python :: 3.12
Classifier: Programming Language :: Python :: 3.13
Requires-Python: <4,>=3.9
License-File: LICENSE
Requires-Dist: clickhouse-driver>=0.2.2
Provides-Extra: testing
Requires-Dist: pytest==8.4.1; extra == "testing"
Requires-Dist: pytest-cov==6.2.1; extra == "testing"
Dynamic: license-file
